{
    "id": "51f2c2df-2178-410e-aff6-7196e70713c4",
    "title": "Roir'Daiintuz",
    "slug": "roir-daiintuz-species",
    "state": "public",
    "isWip": true,
    "isDraft": false,
    "entityClass": "Species",
    "icon": "fa-solid fa-file",
    "url": "https://www.worldanvil.com/w/nixxia-slemme/a/roir-daiintuz-species",
    "subscribergroups": [],
    "folderId": "-1",
    "tags": "",
    "updateDate": {
        "date": "2025-04-27 16:03:03.000000",
        "timezone_type": 3,
        "timezone": "Europe/London"
    },
    "position": null,
    "excerpt": null,
    "wordcount": 320,
    "creationDate": {
        "date": "2024-02-01 12:15:57.000000",
        "timezone_type": 3,
        "timezone": "Europe/London"
    },
    "publicationDate": {
        "date": "2024-02-07 16:14:17.000000",
        "timezone_type": 3,
        "timezone": "Europe/London"
    },
    "notificationDate": null,
    "likes": null,
    "views": 16,
    "userMetadata": null,
    "articleMetadata": null,
    "cssClasses": null,
    "displayCss": null,
    "templateType": "species",
    "customArticleTemplate": null,
    "editor": "plutarch",
    "content": "[p]Created at the twilight of @[The War of One and All](Article:6c05237a-08f1-43ef-b98e-2b0d3adf2c75), the @[Roir'Daiintuz](Article:51f2c2df-2178-410e-aff6-7196e70713c4) are ancient constructs of magic wrought by the @[Hah'Slen](Article:ff2a03e9-c82b-457b-ae70-9accb480f52a). Forged not as living beings, but as manifestations of balance, they were designed to be tools of equilibrium within the @[Yoos'Okaaz](Article:11de30cd-0459-4619-9739-b3afbfa6835c), the Arcane Sea.[/p]\r\n[p][/p]\r\n[p][/p]\r\n[p]When the @[Rúth'Sunvaar](Article:8dfacf74-bff9-4f00-a37d-bf84b4c3e0f5) launched devastating assaults upon the Yoos'Okaaz — corrupting its currents, distorting its realms — the Hah'Slen acted. Unable to leave the @[Fir'Gol](Article:d80be528-2ddc-448d-9474-9ff2203f3c4a) (the Material Plane) themselves to intervene directly, they instead wove the Roir'Daiintuz from the raw essence of stability and resistance. These entities became the silent stewards of the Arcane Sea, countering the chaos the Rúth'Sunvaar sought to unleash.[/p]\r\n[p][/p]\r\n[p]To mortal minds, the Roir'Daiintuz are little more than a force of nature. They have no known shape or voice. They move unseen among the ever-shifting tides of magic, repairing rents, stilling storms, and quieting corrupted magics before they can spill into other realms. Scholars of magic sometimes whisper of \"the hand of the balance\" or \"the silent current,\" but no true record of their existence has ever been proven — only the feeling that something answers when imbalance looms too large.[/p]\r\n[p][/p]\r\n[p]Even now, long after the War of One and All has passed into myth, the Roir'Daiintuz persist. Ageless, voiceless, tireless, they continue the duty given to them at the world's first great breaking: to ensure that neither ambition nor rage can tear the Arcane Sea apart.[/p]\r\n[p][/p]",
    "author": {
        "id": "55c968f3-82a0-4acf-971e-6dc4164d9531",
        "title": "slemme",
        "slug": null,
        "state": null,
        "isWip": null,
        "isDraft": null,
        "entityClass": "User",
        "icon": "fa-solid fa-user",
        "url": "https://www.worldanvil.com/author/slemme",
        "subscribergroups": [],
        "folderId": null,
        "tags": null,
        "updateDate": null
    },
    "category": {
        "id": "eee57958-5f3d-4dd4-b662-f884f66a6564",
        "title": "Sentient",
        "slug": "sentient-category",
        "state": "public",
        "isWip": null,
        "isDraft": null,
        "entityClass": "Category",
        "icon": "fa-solid fa-folder",
        "url": "https://www.worldanvil.com/w/nixxia-slemme/c/sentient-category",
        "subscribergroups": [],
        "folderId": null,
        "tags": null,
        "updateDate": {
            "date": "2025-07-22 16:46:28.000000",
            "timezone_type": 3,
            "timezone": "Europe/London"
        }
    },
    "world": {
        "id": "3bb21e6d-c322-4fc6-b444-40d355e70c3e",
        "title": "Nixxia",
        "slug": "nixxia-slemme",
        "state": "public",
        "isWip": null,
        "isDraft": null,
        "entityClass": "World",
        "icon": "fa-solid fa-globe-stand",
        "url": "https://www.worldanvil.com/w/nixxia-slemme",
        "subscribergroups": [
            {
                "id": "314300fc-d4c6-4472-a987-1ddc66cd1576",
                "title": "Friends",
                "slug": null,
                "state": null,
                "entityClass": "SubscriberGroup",
                "icon": null,
                "url": null,
                "subscribergroups": []
            }
        ],
        "folderId": "-1",
        "tags": "",
        "updateDate": {
            "date": "2025-12-18 14:12:56.000000",
            "timezone_type": 3,
            "timezone": "Europe/London"
        }
    },
    "articleParent": null,
    "cover": {
        "id": 1251432,
        "title": "Nixxia world cover",
        "slug": null,
        "state": "public",
        "isWip": null,
        "isDraft": null,
        "entityClass": "Image",
        "icon": "fa-solid fa-image",
        "url": "https://www.worldanvil.com/uploads/images/9b9659a14869c65e79973202b1b806e9.jpg",
        "subscribergroups": [],
        "folderId": "-1",
        "tags": "",
        "updateDate": {
            "date": "2020-07-02 23:27:01.000000",
            "timezone_type": 3,
            "timezone": "Europe/London"
        }
    },
    "coverSource": "World",
    "pronunciation": null,
    "snippet": null,
    "seeded": null,
    "sidebarcontent": null,
    "sidepanelcontenttop": null,
    "sidepanelcontent": null,
    "sidebarcontentbottom": null,
    "footnotes": null,
    "fullfooter": null,
    "authornotes": null,
    "scrapbook": null,
    "credits": null,
    "displaySidebar": true,
    "articleNext": null,
    "articlePrevious": null,
    "timeline": null,
    "prompt": null,
    "gallery": null,
    "block": null,
    "orgchart": null,
    "showSeeded": false,
    "webhookUpdate": false,
    "communityUpdate": false,
    "commentPlaceholder": null,
    "passcodecta": null,
    "metaTitle": null,
    "metaDescription": null,
    "subheading": "ROÍ'DAÎNTUZ",
    "coverIsMap": false,
    "isFeaturedArticle": false,
    "isAdultContent": false,
    "isLocked": false,
    "allowComments": true,
    "allowContentCopy": false,
    "showInToc": true,
    "isEmphasized": false,
    "displayAuthor": false,
    "displayChildrenUnder": true,
    "displayTitle": true,
    "displaySheet": true,
    "badge": null,
    "editURL": "https://www.worldanvil.com/world/species/51f2c2df-2178-410e-aff6-7196e70713c4/edit",
    "trinominal": null,
    "ancenstry": null,
    "lifespan": null,
    "anatomy": null,
    "perception": null,
    "genetics": null,
    "ecology": null,
    "diet": null,
    "domestication": null,
    "uses": null,
    "biocycle": null,
    "growthrate": null,
    "symbiotic": null,
    "isSentient": false,
    "isIntelligent": false,
    "geographicalOrigin": null,
    "averageIntelligence": null,
    "averagePhysique": null,
    "facialCharacteristics": null,
    "skinHairColor": null,
    "traits": null,
    "averageHeight": null,
    "averageWeight": null,
    "averageLength": null,
    "namingTraditions": null,
    "firstnamesMale": null,
    "firstnamesFemale": null,
    "lastnames": null,
    "majorReligions": null,
    "majorOrganizations": null,
    "beautyIdeals": null,
    "genderIdeals": null,
    "courtshipIdeals": null,
    "relationshipsIdeals": null,
    "technologicalLevel": null,
    "languages": null,
    "etiquette": null,
    "dresscode": null,
    "culture": null,
    "customs": null,
    "taboos": null,
    "history": null,
    "socialstructure": null,
    "mythsAndLegends": null,
    "historicalFigures": null,
    "interspeciesRelations": null,
    "isExtinct": false,
    "conservation": null,
    "behaviour": null,
    "datasheet": null,
    "discoverer": null,
    "children": [
        {
            "id": "b444b9f6-2bca-4934-86c6-56ce10c53fd0",
            "title": "Nil'Thur",
            "slug": "nil-thur-species",
            "state": "public",
            "isWip": true,
            "isDraft": false,
            "entityClass": "Species",
            "icon": "fa-solid fa-file",
            "url": "https://www.worldanvil.com/w/nixxia-slemme/a/nil-thur-species",
            "subscribergroups": [],
            "folderId": "eee57958-5f3d-4dd4-b662-f884f66a6564",
            "tags": null,
            "updateDate": {
                "date": "2025-04-27 16:33:37.000000",
                "timezone_type": 3,
                "timezone": "Europe/London"
            }
        }
    ],
    "isEditable": true,
    "success": true
}