{
    "id": "1fc72c51-3523-4506-9161-33e1d86f6748",
    "title": "Mermaids - Overview",
    "slug": "mermaids---overview-species",
    "state": "public",
    "isWip": true,
    "isDraft": false,
    "entityClass": "Species",
    "icon": "fa-solid fa-file",
    "url": "https://www.worldanvil.com/w/nixxia-slemme/a/mermaids---overview-species",
    "subscribergroups": [],
    "folderId": "-1",
    "tags": "",
    "updateDate": {
        "date": "2024-02-13 00:04:09.000000",
        "timezone_type": 3,
        "timezone": "Europe/London"
    },
    "position": null,
    "excerpt": null,
    "wordcount": 325,
    "creationDate": {
        "date": "2024-02-13 00:01:16.000000",
        "timezone_type": 3,
        "timezone": "Europe/London"
    },
    "publicationDate": {
        "date": "2024-02-13 00:01:16.000000",
        "timezone_type": 3,
        "timezone": "Europe/London"
    },
    "notificationDate": null,
    "likes": null,
    "views": 47,
    "userMetadata": null,
    "articleMetadata": null,
    "cssClasses": null,
    "displayCss": null,
    "templateType": "species",
    "customArticleTemplate": null,
    "editor": "wysiwyg",
    "content": "The Mermaids of Nixxia's oceans are a fascinating amalgamation of ethereal beauty and primal wildness, born from the ancient lineage of the Zaetaedhel, yet transformed by the mysterious depths they inhabit. With their upper halves resembling the graceful elegance of the Zaetaedhel elves and their lower halves adorned with traits reminiscent of sea creatures like fish or crabs, the Mermaids embody a mesmerizing duality of land and sea.\r\n\r\nTheir upper bodies boast the delicate features and luminous skin of their Zaetaedhel ancestors, with expressive eyes that gleam with the wisdom of the ocean's depths. Their slender forms are adorned with bioluminescent patterns that shimmer and dance like underwater constellations, reflecting their affinity for the mysteries of the deep.\r\n\r\nBelow the waist, the Mermaids' lower halves transform into an array of aquatic forms, each uniquely adapted to their oceanic realm. Some possess sinuous tails that undulate with the fluidity of kelp forests, while others boast the armored shells and scuttling legs of crustaceans, allowing them to navigate the rugged terrain of the ocean floor with ease.\r\n\r\nLiving predominantly in the deep reaches of Nixxia's oceans, the Mermaids exist in a state of primal instinct and untamed beauty. While not inherently hostile, their feral nature is a testament to their symbiotic relationship with the untamed forces of the sea. They move with a fluid grace through the dark abyss, their senses attuned to the ebb and flow of underwater currents and the secrets hidden within the ocean's depths.\r\n\r\nDespite their wild demeanor, the Mermaids retain echoes of their Zaetaedhel heritage, exhibiting glimpses of curiosity and intrigue towards the world above the waves. Their interactions with surface dwellers are fleeting and enigmatic, marked by elusive glimpses and haunting melodies that echo across the ocean's expanse.\r\n\r\nIn the realm of Nixxia's oceans, the Mermaids are both guardians and enigmas, embodying the enduring mysteries and untamed beauty of the deep sea.",
    "author": {
        "id": "55c968f3-82a0-4acf-971e-6dc4164d9531",
        "title": "slemme",
        "slug": null,
        "state": null,
        "isWip": null,
        "isDraft": null,
        "entityClass": "User",
        "icon": "fa-solid fa-user",
        "url": "https://www.worldanvil.com/author/slemme",
        "subscribergroups": [],
        "folderId": null,
        "tags": null,
        "updateDate": null
    },
    "category": {
        "id": "9e748b8c-9f03-4729-bb39-b2dd27e4b61b",
        "title": "Monsters",
        "slug": "monster-category",
        "state": "public",
        "isWip": null,
        "isDraft": null,
        "entityClass": "Category",
        "icon": "ra ra-dragon",
        "url": "https://www.worldanvil.com/w/nixxia-slemme/c/monster-category",
        "subscribergroups": [
            {
                "id": "314300fc-d4c6-4472-a987-1ddc66cd1576",
                "title": "Friends",
                "slug": null,
                "state": null,
                "entityClass": "SubscriberGroup",
                "icon": null,
                "url": null,
                "subscribergroups": []
            }
        ],
        "folderId": null,
        "tags": null,
        "updateDate": {
            "date": "2025-06-24 08:59:19.000000",
            "timezone_type": 3,
            "timezone": "Europe/London"
        }
    },
    "world": {
        "id": "3bb21e6d-c322-4fc6-b444-40d355e70c3e",
        "title": "Nixxia",
        "slug": "nixxia-slemme",
        "state": "public",
        "isWip": null,
        "isDraft": null,
        "entityClass": "World",
        "icon": "fa-solid fa-globe-stand",
        "url": "https://www.worldanvil.com/w/nixxia-slemme",
        "subscribergroups": [
            {
                "id": "314300fc-d4c6-4472-a987-1ddc66cd1576",
                "title": "Friends",
                "slug": null,
                "state": null,
                "entityClass": "SubscriberGroup",
                "icon": null,
                "url": null,
                "subscribergroups": []
            }
        ],
        "folderId": "-1",
        "tags": "",
        "updateDate": {
            "date": "2025-12-18 14:12:56.000000",
            "timezone_type": 3,
            "timezone": "Europe/London"
        }
    },
    "articleParent": null,
    "cover": {
        "id": 1251432,
        "title": "Nixxia world cover",
        "slug": null,
        "state": "public",
        "isWip": null,
        "isDraft": null,
        "entityClass": "Image",
        "icon": "fa-solid fa-image",
        "url": "https://www.worldanvil.com/uploads/images/9b9659a14869c65e79973202b1b806e9.jpg",
        "subscribergroups": [],
        "folderId": "-1",
        "tags": "",
        "updateDate": {
            "date": "2020-07-02 23:27:01.000000",
            "timezone_type": 3,
            "timezone": "Europe/London"
        }
    },
    "coverSource": "World",
    "pronunciation": null,
    "snippet": null,
    "seeded": null,
    "sidebarcontent": null,
    "sidepanelcontenttop": "[img:5339921]",
    "sidepanelcontent": null,
    "sidebarcontentbottom": null,
    "footnotes": null,
    "fullfooter": null,
    "authornotes": null,
    "scrapbook": null,
    "credits": null,
    "displaySidebar": true,
    "articleNext": null,
    "articlePrevious": null,
    "timeline": null,
    "prompt": null,
    "gallery": null,
    "block": null,
    "orgchart": null,
    "showSeeded": false,
    "webhookUpdate": false,
    "communityUpdate": false,
    "commentPlaceholder": null,
    "passcodecta": null,
    "metaTitle": null,
    "metaDescription": null,
    "subheading": "PELZAÄDHeL",
    "coverIsMap": false,
    "isFeaturedArticle": false,
    "isAdultContent": false,
    "isLocked": false,
    "allowComments": true,
    "allowContentCopy": false,
    "showInToc": true,
    "isEmphasized": false,
    "displayAuthor": false,
    "displayChildrenUnder": true,
    "displayTitle": true,
    "displaySheet": true,
    "badge": null,
    "editURL": "https://www.worldanvil.com/world/species/1fc72c51-3523-4506-9161-33e1d86f6748/edit",
    "trinominal": "Aedhelkys Pelzaokaaz",
    "ancenstry": null,
    "lifespan": null,
    "anatomy": null,
    "perception": null,
    "genetics": null,
    "ecology": null,
    "diet": null,
    "domestication": null,
    "uses": null,
    "biocycle": null,
    "growthrate": null,
    "symbiotic": null,
    "isSentient": false,
    "isIntelligent": false,
    "geographicalOrigin": null,
    "averageIntelligence": null,
    "averagePhysique": null,
    "facialCharacteristics": null,
    "skinHairColor": null,
    "traits": null,
    "averageHeight": null,
    "averageWeight": null,
    "averageLength": null,
    "namingTraditions": null,
    "firstnamesMale": null,
    "firstnamesFemale": null,
    "lastnames": null,
    "majorReligions": null,
    "majorOrganizations": null,
    "beautyIdeals": null,
    "genderIdeals": null,
    "courtshipIdeals": null,
    "relationshipsIdeals": null,
    "technologicalLevel": null,
    "languages": null,
    "etiquette": null,
    "dresscode": null,
    "culture": null,
    "customs": null,
    "taboos": null,
    "history": null,
    "socialstructure": null,
    "mythsAndLegends": null,
    "historicalFigures": null,
    "interspeciesRelations": null,
    "isExtinct": false,
    "conservation": null,
    "behaviour": null,
    "datasheet": null,
    "discoverer": null,
    "parents": [
        {
            "id": "3cf3a5bf-4847-467b-a3ca-766ef8363024",
            "title": "Zaetaedhel",
            "slug": "zaetaedhel-species",
            "state": "public",
            "isWip": true,
            "isDraft": false,
            "entityClass": "Species",
            "icon": "ra ra-trident",
            "url": "https://www.worldanvil.com/w/nixxia-slemme/a/zaetaedhel-species",
            "subscribergroups": [],
            "folderId": "-1",
            "tags": "",
            "updateDate": {
                "date": "2025-11-13 11:25:15.000000",
                "timezone_type": 3,
                "timezone": "Europe/London"
            }
        }
    ],
    "isEditable": true,
    "success": true
}